gemsembler/__init__.py
gemsembler/__main__.py
gemsembler/anticreation.py
gemsembler/comparison.py
gemsembler/conversion.py
gemsembler/creation.py
gemsembler/curation.py
gemsembler/dbs.py
gemsembler/downstream.py
gemsembler/drawing.py
gemsembler/gathering.py
gemsembler/general.py
gemsembler/genes.py
gemsembler/pathsfinding.py
gemsembler/periplasmic.py
gemsembler/quickdiff.py
gemsembler/selection.py
gemsembler/structural.py
gemsembler/data/__init__.py
gemsembler/data/masses_and_charges.json
gemsembler/data/BU/BU_agora.xml.gz
gemsembler/data/BU/BU_carveme_hom.xml.gz
gemsembler/data/BU/BU_gapseq.xml.gz
gemsembler/data/BU/BU_modelSEED.sbml.gz
gemsembler/data/BU/__init__.py
gemsembler/data/LP/LP_agora_model.xml.gz
gemsembler/data/LP/LP_carveme_model.xml.gz
gemsembler/data/LP/LP_gapseq_model.xml.gz
gemsembler/data/LP/LP_genome.faa.gz
gemsembler/data/LP/LP_genome.fna.gz
gemsembler/data/LP/LP_genome_agora.fna.gz
gemsembler/data/LP/LP_modelseed_model.xml.gz
gemsembler/data/LP/__init__.py
gemsembler-0.11.12.dist-info/licenses/LICENSE
gemsembler-0.11.12.dist-info/METADATA
gemsembler-0.11.12.dist-info/WHEEL
gemsembler-0.11.12.dist-info/entry_points.txt
gemsembler-0.11.12.dist-info/top_level.txt
gemsembler-0.11.12.dist-info/RECORD
