Metadata-Version: 2.4
Name: gemsembler
Version: 0.11.12
Summary: A tool for assembling and comparing several types of Genome-Scale Metabolic Models.
Author-email: Elena Matveishina <elena.matveishina@embl.de>, Bartosz Bartmanski <bartosz.bartmanski@embl.de>
License: MIT License
Project-URL: Homepage, https://git.embl.de/grp-zimmermann-kogadeeva/GEMsembler
Project-URL: Bug tracker, https://git.embl.de/grp-zimmermann-kogadeeva/GEMsembler/issues
Keywords: genome scale metabolic models,metabolism,biology
Classifier: Intended Audience :: Science/Research
Classifier: Topic :: Scientific/Engineering :: Bio-Informatics
Classifier: Programming Language :: Python :: 3
Classifier: License :: OSI Approved :: MIT License
Classifier: Operating System :: OS Independent
Requires-Python: >=3.9
License-File: LICENSE
Requires-Dist: cobra
Requires-Dist: metquest
Requires-Dist: dill
Requires-Dist: ncbi-genome-download
Requires-Dist: numpy
Requires-Dist: scipy
Requires-Dist: networkx
Requires-Dist: pandas>=2.1
Requires-Dist: pyarrow
Requires-Dist: seaborn
Requires-Dist: pyvis
Requires-Dist: h5py
Requires-Dist: platformdirs
Requires-Dist: pyyaml
Dynamic: license-file
